{
    "Temperate Conifer Forests": "TemperateConiferForests.jpg",
    "Temperate Grasslands, Savannas & Shrublands": "TemperateGrasslands.jpg",
    "Temperate Broadleaf & Mixed Forests": "TemperateBroadleaf.jpg",
    "Mediterranean Forests, Woodlands & Scrub": "CaliforniaInteriorChaparral.jpg",
    "Deserts & Xeric Shrublands": "Deserts.jpg",
    "Tundra": "Tundra.jpg",
    "Tropical & Subtropical Coniferous Forests": "Tropical.jpg",
    "Tropical & Subtropical Grasslands, Savannas & Shrublands": "Tropical.jpg",
    "Mangroves": "Mangroves.jpg"
}